odoo/addons/product_english_name/README.rst
odoo/addons/product_english_name/__init__.py
odoo/addons/product_english_name/__manifest__.py
odoo/addons/product_english_name/i18n/it.po
odoo/addons/product_english_name/i18n/product_english_name.pot
odoo/addons/product_english_name/models/__init__.py
odoo/addons/product_english_name/models/product_template.py
odoo/addons/product_english_name/readme/CONFIGURE.rst
odoo/addons/product_english_name/readme/CONTRIBUTORS.rst
odoo/addons/product_english_name/readme/DESCRIPTION.rst
odoo/addons/product_english_name/security/groups.xml
odoo/addons/product_english_name/static/description/icon.png
odoo/addons/product_english_name/static/description/index.html
odoo/addons/product_english_name/static/description/screen_english.png
odoo/addons/product_english_name/static/description/screen_french.png
odoo/addons/product_english_name/views/product_template.xml
odoo_addon_product_english_name-16.0.1.0.0.4.dist-info/METADATA
odoo_addon_product_english_name-16.0.1.0.0.4.dist-info/WHEEL
odoo_addon_product_english_name-16.0.1.0.0.4.dist-info/top_level.txt
odoo_addon_product_english_name-16.0.1.0.0.4.dist-info/RECORD
